{"user": {"id": "5828706619", "screen_name": "狂龙十八段", "gender": "m", "birthday": "", "location": "", "education": "", "company": "", "registration_time": "", "sunshine": "", "statuses_count": 4268, "followers_count": 925000, "follow_count": 115, "description": "简单炒股，快乐生活，资金流派，极致打法", "profile_url": "https://m.weibo.cn/u/5828706619?", "profile_image_url": "https://tva2.sinaimg.cn/crop.0.0.179.179.180/006msER5gw1f25exzhnpuj3050050aab.jpg?KID=imgbed,tva&Expires=1705574840&ssig=rR%2FKfZPoDw", "avatar_hd": "https://ww2.sinaimg.cn/orj480/006msER5gw1f25exzhnpuj3050050aab.jpg", "urank": 38, "mbrank": 2, "verified": true, "verified_type": 0, "verified_reason": "财经博主 头条文章作者"}, "weibo": [{"user_id": 5828706619, "screen_name": "狂龙十八段", "id": 4989303698752417, "bid": "NBtcdAIU1", "text": "虽然是看不到持续性的反弹 但是很好了\n新能源也该企稳 很多分支其实未来增速也很不错 ", "article_url": "", "pics": "https://wx4.sinaimg.cn/large/006msER5gy1hlqmp0ehi4j30zu1og12g.jpg", "video_url": "", "location": "", "created_at": "2024-01-12T10:22:41", "source": "iPhone 14 Pro Max", "attitudes_count": 618, "comments_count": 0, "reposts_count": 9, "topics": "", "at_users": "", "full_created_at": "2024-01-12 10:22:41"}, {"user_id": 5828706619, "screen_name": "狂龙十八段", "id": 4990451035669034, "bid": "NBX2LnMM2", "text": "量能还在跌，大家都懂 ", "article_url": "", "pics": "https://wx4.sinaimg.cn/large/006msER5gy1hluahrl8j2j30tp0kj43z.jpg", "video_url": "", "location": "", "created_at": "2024-01-15T14:21:47", "source": "微博网页版", "attitudes_count": 463, "comments_count": 0, "reposts_count": 5, "topics": "", "at_users": "", "full_created_at": "2024-01-15 14:21:47"}, {"user_id": 5828706619, "screen_name": "狂龙十八段", "id": 4990398892084736, "bid": "NBVGF8KkM", "text": "很平均的反弹\n ", "article_url": "", "pics": "https://wx4.sinaimg.cn/large/006msER5gy1hlu4i6rs87j30zu25onjx.jpg", "video_url": "", "location": "", "created_at": "2024-01-15T10:54:36", "source": "iPhone 14 Pro Max", "attitudes_count": 441, "comments_count": 0, "reposts_count": 4, "topics": "", "at_users": "", "full_created_at": "2024-01-15 10:54:36"}, {"user_id": 5828706619, "screen_name": "狂龙十八段", "id": 4990381057907110, "bid": "NBVdTxb02", "text": "消费类的复苏预期，虽然是在炒股价\n但实际大家对经济的预期，以及增长，都。。。。 ", "article_url": "", "pics": "", "video_url": "", "location": "", "created_at": "2024-01-15T09:43:44", "source": "微博网页版", "attitudes_count": 596, "comments_count": 0, "reposts_count": 3, "topics": "", "at_users": "", "full_created_at": "2024-01-15 09:43:44"}, {"user_id": 5828706619, "screen_name": "狂龙十八段", "id": 4990380402278423, "bid": "NBVcQ9yIL", "text": "零散，无太大突出热点\n继续缩量，无聊的行情 ", "article_url": "", "pics": "", "video_url": "", "location": "", "created_at": "2024-01-15T09:41:06", "source": "微博网页版", "attitudes_count": 479, "comments_count": 0, "reposts_count": 3, "topics": "", "at_users": "", "full_created_at": "2024-01-15 09:41:06"}, {"user_id": 5828706619, "screen_name": "狂龙十八段", "id": 4990377062303327, "bid": "NBV7s9Fcr", "text": "业绩超预期的锦泓集团，全市场顶的最死，意味着业绩潮炒作来临 ", "article_url": "", "pics": "", "video_url": "", "location": "", "created_at": "2024-01-15T09:27:51", "source": "微博网页版", "attitudes_count": 532, "comments_count": 0, "reposts_count": 4, "topics": "", "at_users": "", "full_created_at": "2024-01-15 09:27:51"}, {"user_id": 5828706619, "screen_name": "狂龙十八段", "id": 4990820941302195, "bid": "NC6Fo5sL9", "text": "收盘给个总结吧\n盘中资金老三样，大金融护盘，北交所充当情绪炒作\n但是，普遍个股，依旧普跌。。。 ", "article_url": "", "pics": "https://wx4.sinaimg.cn/large/006msER5gy1hlvgz9dn68j30sm0ifae8.jpg", "video_url": "", "location": "", "created_at": "2024-01-16T14:51:40", "source": "微博网页版", "attitudes_count": 436, "comments_count": 0, "reposts_count": 2, "topics": "", "at_users": "", "full_created_at": "2024-01-16 14:51:40"}, {"user_id": 5828706619, "screen_name": "狂龙十八段", "id": 4990747759087965, "bid": "NC4LlC8c5", "text": "光伏、锂电、储能反弹，新能源的低位反弹轮动行情 ", "article_url": "", "pics": "", "video_url": "", "location": "", "created_at": "2024-01-16T10:00:52", "source": "微博网页版", "attitudes_count": 628, "comments_count": 0, "reposts_count": 6, "topics": "", "at_users": "", "full_created_at": "2024-01-16 10:00:52"}, {"user_id": 5828706619, "screen_name": "狂龙十八段", "id": 4990739991235624, "bid": "NC4yP5brq", "text": "竞价无热点，不知道大家适不适应，以前竞价总有一些题材冒出来，开盘后很强势\n但最后一个月，因为基金净卖出管制，也因为快要过年大缩量，每天竞价都是平平无奇，天天围绕着几个情绪公认龙头怼，要嘛跌停，要嘛涨停 ", "article_url": "", "pics": "", "video_url": "", "location": "", "created_at": "2024-01-16T09:30:00", "source": "微博网页版", "attitudes_count": 557, "comments_count": 0, "reposts_count": 2, "topics": "", "at_users": "", "full_created_at": "2024-01-16 09:30:00"}, {"user_id": 5828706619, "screen_name": "狂龙十八段", "id": 4991185697637353, "bid": "NCg9Hw2P7", "text": "好累啊。。这样的盘面\n好累，好累 ", "article_url": "", "pics": "", "video_url": "", "location": "", "created_at": "2024-01-17T15:01:05", "source": "微博网页版", "attitudes_count": 812, "comments_count": 0, "reposts_count": 6, "topics": "", "at_users": "", "full_created_at": "2024-01-17 15:01:05"}, {"user_id": 5828706619, "screen_name": "狂龙十八段", "id": 4991165988340737, "bid": "NCfDUyZO1", "text": "大A啊，不看不行，看了更头痛 ", "article_url": "", "pics": "", "video_url": "", "location": "", "created_at": "2024-01-17T13:42:46", "source": "微博网页版", "attitudes_count": 800, "comments_count": 0, "reposts_count": 3, "topics": "", "at_users": "", "full_created_at": "2024-01-17 13:42:46"}, {"user_id": 5828706619, "screen_name": "狂龙十八段", "id": 4991104415960663, "bid": "NCe2Bp0DJ", "text": "客观看数据的话，昨天的资金救市，其实在收盘中，反映在中国50三倍做空指数上，是不看好市场的，所以昨晚做空指数大涨\n为什么会产生这个预期？因为护盘的资金并未明确，场内大家股民没信心，如果这个护盘是持续性的，连拉它个三五天的，可能有一点作用，要是像历史上只拉一天，作用是有限的 ", "article_url": "", "pics": "", "video_url": "", "location": "", "created_at": "2024-01-17T09:38:06", "source": "微博网页版", "attitudes_count": 720, "comments_count": 0, "reposts_count": 20, "topics": "", "at_users": "", "full_created_at": "2024-01-17 09:38:06"}, {"user_id": 5828706619, "screen_name": "狂龙十八段", "id": 4991547680490802, "bid": "NCpzy23Ga", "text": "心情还行 ", "article_url": "", "pics": "https://wx4.sinaimg.cn/large/006msER5gy1hlxsg04e6hj32c0340x6p.jpg", "video_url": "", "location": "", "created_at": "2024-01-18T14:59:28", "source": "iPhone 14 Pro Max", "attitudes_count": 321, "comments_count": 0, "reposts_count": 1, "topics": "", "at_users": "", "full_created_at": "2024-01-18 14:59:28"}, {"user_id": 5828706619, "screen_name": "狂龙十八段", "id": 4991545164172287, "bid": "NCpvuhvoX", "text": "干大空头 不容易啊\ngjd也是难 多点理解 ", "article_url": "", "pics": "", "video_url": "", "location": "", "created_at": "2024-01-18T14:49:28", "source": "iPhone 14 Pro Max", "attitudes_count": 488, "comments_count": 0, "reposts_count": 1, "topics": "", "at_users": "", "full_created_at": "2024-01-18 14:49:28"}, {"user_id": 5828706619, "screen_name": "狂龙十八段", "id": 4991542324370021, "bid": "NCpqUikQd", "text": "虽有小回暖 但是大量的股票还是在阴跌 ", "article_url": "", "pics": "https://wx4.sinaimg.cn/large/006msER5gy1hlxrtglio5j30zu25oqgo.jpg", "video_url": "", "location": "", "created_at": "2024-01-18T14:38:11", "source": "iPhone 14 Pro Max", "attitudes_count": 293, "comments_count": 0, "reposts_count": 2, "topics": "", "at_users": "", "full_created_at": "2024-01-18 14:38:11"}, {"user_id": 5828706619, "screen_name": "狂龙十八段", "id": 4991534880002639, "bid": "NCpeU00Gz", "text": "这几天花了好多钱去救市\n肉眼可见的 ", "article_url": "", "pics": "", "video_url": "", "location": "", "created_at": "2024-01-18T14:08:36", "source": "iPhone 14 Pro Max", "attitudes_count": 542, "comments_count": 0, "reposts_count": 7, "topics": "", "at_users": "", "full_created_at": "2024-01-18 14:08:36"}, {"user_id": 5828706619, "screen_name": "狂龙十八段", "id": 4991530752543909, "bid": "NCp8faFMN", "text": "分享图片 ", "article_url": "", "pics": "https://wx2.sinaimg.cn/large/006msER5gy1hlxqi18k9xj30wq1bk0vl.jpg", "video_url": "", "location": "", "created_at": "2024-01-18T13:52:12", "source": "iPhone 14 Pro Max", "attitudes_count": 391, "comments_count": 0, "reposts_count": 5, "topics": "", "at_users": "", "full_created_at": "2024-01-18 13:52:12"}, {"user_id": 5828706619, "screen_name": "狂龙十八段", "id": 4991483650246809, "bid": "NCnUh12cN", "text": "不救回来 会出连环问题的 ", "article_url": "", "pics": "", "video_url": "", "location": "", "created_at": "2024-01-18T10:45:02", "source": "iPhone 14 Pro Max", "attitudes_count": 936, "comments_count": 0, "reposts_count": 21, "topics": "", "at_users": "", "full_created_at": "2024-01-18 10:45:02"}, {"user_id": 5828706619, "screen_name": "狂龙十八段", "id": 4991473703715050, "bid": "NCnEefAsa", "text": "就是这个剧本 但是要一举作气翻红才有用 ", "article_url": "", "pics": "", "video_url": "", "location": "", "created_at": "2024-01-18T10:05:30", "source": "iPhone 14 Pro Max", "attitudes_count": 746, "comments_count": 0, "reposts_count": 6, "topics": "", "at_users": "", "full_created_at": "2024-01-18 10:05:30"}, {"user_id": 5828706619, "screen_name": "狂龙十八段", "id": 4991464562492365, "bid": "NCnpuasnr", "text": "顺势的低开，开盘估计有顺势的快速下探，今天很关键了\n历史上的这种走势，只要盘中有资金坚决V回来，是可以形成小底部的 ", "article_url": "", "pics": "", "video_url": "", "location": "", "created_at": "2024-01-18T09:29:11", "source": "微博网页版", "attitudes_count": 773, "comments_count": 0, "reposts_count": 4, "topics": "", "at_users": "", "full_created_at": "2024-01-18 09:29:11"}]}